pycytominer/__about__.py
pycytominer/__config__.py
pycytominer/__init__.py
pycytominer/aggregate.py
pycytominer/annotate.py
pycytominer/consensus.py
pycytominer/cyto_utils/DeepProfiler_processing.py
pycytominer/cyto_utils/__init__.py
pycytominer/cyto_utils/anndata_utils.py
pycytominer/cyto_utils/annotate_custom.py
pycytominer/cyto_utils/cell_locations.py
pycytominer/cyto_utils/cell_locations_cmd.py
pycytominer/cyto_utils/cells.py
pycytominer/cyto_utils/collate.py
pycytominer/cyto_utils/collate_cmd.py
pycytominer/cyto_utils/cp_image_features.py
pycytominer/cyto_utils/database_config/ingest_config.ini
pycytominer/cyto_utils/features.py
pycytominer/cyto_utils/load.py
pycytominer/cyto_utils/modz.py
pycytominer/cyto_utils/output.py
pycytominer/cyto_utils/single_cell_ingest_utils.py
pycytominer/cyto_utils/util.py
pycytominer/cyto_utils/write_gct.py
pycytominer/data/blocklist_features.txt
pycytominer/data/metadata_feature_dictionary.txt
pycytominer/feature_select.py
pycytominer/normalize.py
pycytominer/operations/__init__.py
pycytominer/operations/correlation_threshold.py
pycytominer/operations/get_na_columns.py
pycytominer/operations/noise_removal.py
pycytominer/operations/transform.py
pycytominer/operations/variance_threshold.py
pycytominer-1.3.1.dist-info/METADATA
pycytominer-1.3.1.dist-info/WHEEL
pycytominer-1.3.1.dist-info/licenses/LICENSE.md
pycytominer-1.3.1.dist-info/RECORD
