Metadata-Version: 2.4
Name: pycytominer
Version: 1.3.1
Summary: Python package for processing image-based profiling data
License: BSD-3-Clause
License-File: LICENSE.md
Author: Erik Serrano
Maintainer: Gregory P. Way
Maintainer-email: gregory.way@cuanschutz.edu
Requires-Python: >=3.10,<3.15
Classifier: License :: OSI Approved :: BSD License
Classifier: Programming Language :: Python :: 3
Classifier: Programming Language :: Python :: 3.10
Classifier: Programming Language :: Python :: 3.11
Classifier: Programming Language :: Python :: 3.12
Classifier: Programming Language :: Python :: 3.13
Classifier: Programming Language :: Python :: 3.14
Provides-Extra: anndata
Provides-Extra: cell-locations
Provides-Extra: collate
Requires-Dist: anndata (<0.12.2) ; (python_version < "3.11") and (extra == "anndata")
Requires-Dist: anndata (>=0.12.2) ; (python_version >= "3.11") and (extra == "anndata")
Requires-Dist: boto3 (>=1.26.79) ; extra == "cell-locations"
Requires-Dist: cytominer-database (==0.3.4) ; extra == "collate"
Requires-Dist: fire (>=0.5.0) ; extra == "cell-locations"
Requires-Dist: fsspec (>=2023.1.0) ; extra == "cell-locations"
Requires-Dist: numpy (>=1.16.5)
Requires-Dist: pandas (>=1.2.0)
Requires-Dist: pyarrow (>=8.0.0)
Requires-Dist: s3fs (>=2023.4.0) ; extra == "cell-locations"
Requires-Dist: scikit-learn (>=0.21.2)
Requires-Dist: scipy (>1.13.1) ; python_full_version > "3.12.0"
Requires-Dist: scipy (>=1.5) ; python_version < "3.13"
Requires-Dist: sqlalchemy (>=1.3.6,<3)
Requires-Dist: zarr (<3.1.1) ; (python_version < "3.11") and (extra == "anndata")
Requires-Dist: zarr (>=3.1.1) ; (python_version >= "3.11") and (extra == "anndata")
Project-URL: Homepage, https://pycytominer.readthedocs.io/
Project-URL: Repository, https://github.com/cytomining/pycytominer
